[{"domain": ".github.com", "httpOnly": false, "name": "tz", "path": "/", "sameSite": "Lax", "secure": true, "value": "Asia%2FShanghai"}, {"domain": ".github.com", "expiry": 1750142808, "httpOnly": false, "name": "_octo", "path": "/", "sameSite": "Lax", "secure": true, "value": "GH1.1.2135654418.1718606797"}, {"domain": ".github.com", "httpOnly": false, "name": "preferred_color_mode", "path": "/", "sameSite": "Lax", "secure": true, "value": "light"}, {"domain": ".github.com", "expiry": 1750142808, "httpOnly": true, "name": "logged_in", "path": "/", "sameSite": "Lax", "secure": true, "value": "no"}, {"domain": "github.com", "httpOnly": true, "name": "_gh_sess", "path": "/", "sameSite": "Lax", "secure": true, "value": "9%2FFT1GNXe%2BcAANfohR5MISEAfaWYmjJfc2m8%2BDNscjmPJAq2YWHWeOMF9Ytu7cgfxHrCEsV08ukHSvgfoXnaQz7JVllFfTTaagSKawSn2XYoQ2EkIonnift3KSCcUO1CXWHBEtliqFDJI6Gm205rfpyvSO8dO3jZl0hpwLlkQ%2FoMUcsjIlyp2KIcfCKfMDMuCg%2FDggCkJ1E%2FG663f0CwOlzliEVkhz6cGWbdPCHrdLvMDrcXfpv6Y3OX7HsVkHH%2FYXTFeVV9LuVI3qesFHxv0g%3D%3D--x6%2B2PTAM2K3CM4uG--hNmuFeUFVsZbASFelyzsEw%3D%3D"}]